Metadata-Version: 1.2
Name: BSPython
Version: 1.0.1
Summary: A package enabling BSP in Python
Home-page: https://github.com/Mitchell-Faas/BSPy
Author: Mitchell Faas
Author-email: Faas.Mitchell@gmail.com
License: MIT
Platform: UNKNOWN
Classifier: Programming Language :: Python :: 3
Classifier: License :: OSI Approved :: MIT License
Classifier: Operating System :: OS Independent
Requires-Python: >=3.6
